{"211153408709754880": {"wallet": 50, "bank": 25795, "beg": 0, "give": 0, "pitier": 0}, "164074751172673536": {"wallet": 142, "bank": 0, "beg": 0, "give": 0, "pitier": 0}, "199688749712539648": {"wallet": 670, "bank": 2459, "beg": 0, "give": 0, "pitier": 0}, "159324063834177536": {"wallet": 153, "bank": 2128, "beg": 0, "give": 0, "pitier": 0}, "274650321672732672": {"wallet": 325, "bank": 0, "beg": 0, "give": 0, "pitier": 0}, "426483809589133313": {"wallet": 964, "bank": 892, "beg": 0, "give": 0, "pitier": 0}, "798302007106338839": {"wallet": 235, "bank": 2122503, "beg": 0, "give": 0, "pitier": 0}, "174226896479846400": {"wallet": 850, "bank": 242, "beg": 0, "give": 0, "pitier": 0}, "219468141682491392": {"wallet": 330, "bank": 208, "beg": 0, "give": 0, "pitier": 0}, "348558385551114241": {"wallet": 740, "bank": 0, "beg": 0, "give": 0, "pitier": 0}}