{"211153408709754880": {"wallet": 15, "bank": 4257, "beg": 3, "give": 0, "pitier": 1}, "164074751172673536": {"wallet": 65, "bank": 0, "beg": 0, "give": 0, "pitier": 0}, "199688749712539648": {"wallet": 505, "bank": 231, "beg": 0, "give": 0, "pitier": 0}, "159324063834177536": {"wallet": 40, "bank": 4182, "beg": 3, "give": 0, "pitier": 0}, "274650321672732672": {"wallet": 50, "bank": 1000, "beg": 3, "give": 0, "pitier": 0}, "426483809589133313": {"wallet": 450, "bank": 238, "beg": 0, "give": 0, "pitier": 0}}